README.rst
setup.cfg
setup.py
stmoab/ExperimentDashboard.py
stmoab/StatisticalDashboard.py
stmoab/SummaryDashboard.py
stmoab/__init__.py
stmoab/constants.py
stmoab/utils.py
stmoab.egg-info/PKG-INFO
stmoab.egg-info/SOURCES.txt
stmoab.egg-info/dependency_links.txt
stmoab.egg-info/requires.txt
stmoab.egg-info/top_level.txt