Metadata-Version: 1.0
Name: stmoab
Version: 0.0.7
Summary: A tool for automating a/b testing analysis using stmo dashboards (https://sql.telemetry.mozilla.org)
Home-page: https://github.com/mozilla/stmoab
Author: Marina Samuel
Author-email: msamuel@mozilla.com
License: UNKNOWN
Keywords: stmo,redash,experiments,a/b tests
Platform: UNKNOWN
